setup.py
distributions_mutaz/Binomialdistribution.py
distributions_mutaz/Gaussiandistribution.py
distributions_mutaz/Generaldistribution.py
distributions_mutaz/__init__.py
distributions_mutaz.egg-info/PKG-INFO
distributions_mutaz.egg-info/SOURCES.txt
distributions_mutaz.egg-info/dependency_links.txt
distributions_mutaz.egg-info/not-zip-safe
distributions_mutaz.egg-info/top_level.txt